CMakeLists.txt
LICENSE
MANIFEST.in
README.md
setup.cfg
setup.py
setup_options.py
commonroad_dc/__init__.py
commonroad_dc/__version__.py
commonroad_dc/libcrcc.a
commonroad_dc/libcrccosy.a
commonroad_dc/libgpc.a
commonroad_dc/libtriangle.a
commonroad_dc/pycrcc.cpython-311-x86_64-linux-gnu.so
commonroad_dc/pycrccosy.cpython-311-x86_64-linux-gnu.so
commonroad_dc/__pycache__/__init__.cpython-311.pyc
commonroad_dc/__pycache__/__version__.cpython-311.pyc
commonroad_dc/boundary/__init__.py
commonroad_dc/boundary/boundary.py
commonroad_dc/boundary/construction.py
commonroad_dc/boundary/lanelet_bounds.py
commonroad_dc/boundary/rectangle_builder.py
commonroad_dc/boundary/scenario_bounds.py
commonroad_dc/boundary/triangle_builder.py
commonroad_dc/collision/__init__.py
commonroad_dc/collision/collision_detection/__init__.py
commonroad_dc/collision/collision_detection/minkowski_sum.py
commonroad_dc/collision/collision_detection/pycrcc_collision_dispatch.py
commonroad_dc/collision/collision_detection/scenario.py
commonroad_dc/collision/trajectory_queries/trajectory_queries.py
commonroad_dc/collision/trajectory_queries/trajectory_queries_specialized.py
commonroad_dc/collision/visualization/__init__.py
commonroad_dc/collision/visualization/drawing.py
commonroad_dc/costs/__init__.py
commonroad_dc/costs/evaluation.py
commonroad_dc/costs/partial_cost_functions.py
commonroad_dc/costs/route_matcher.py
commonroad_dc/feasibility/__init__.py
commonroad_dc/feasibility/feasibility_checker.py
commonroad_dc/feasibility/solution_checker.py
commonroad_dc/feasibility/vehicle_dynamics.py
commonroad_dc/geometry/__init__.py
commonroad_dc/geometry/geometry.py
commonroad_dc/geometry/lanelet_ccosy.py
commonroad_dc/geometry/util.py
cpp/CMakeLists.txt
cpp/Readme.txt
cpp/cmake/DrivabilityCheckerConfig.cmake.in
cpp/collision/CMakeLists.txt
cpp/collision/include/collision/application.h
cpp/collision/include/collision/application_settings.h
cpp/collision/include/collision/collision_checker.h
dg_commonroad_drivability_checker.egg-info/PKG-INFO
dg_commonroad_drivability_checker.egg-info/SOURCES.txt
dg_commonroad_drivability_checker.egg-info/dependency_links.txt
dg_commonroad_drivability_checker.egg-info/not-zip-safe
dg_commonroad_drivability_checker.egg-info/requires.txt
dg_commonroad_drivability_checker.egg-info/top_level.txt
