Metadata-Version: 2.1
Name: dg-commonroad-drivability-checker
Version: 2024.1
Summary: Fork of the Drivability checker for CommonRoad scenarios.
Home-page: https://github.com/idsc-frazzoli/commonroad-drivability-checker
Author: IDSC Frazzoli
Author-email: azanardi@ethz.ch
License: BSD
Project-URL: Documentation, https://cps.pages.gitlab.lrz.de/commonroad-drivability-checker/
Project-URL: Forum, https://commonroad.in.tum.de/forum/c/commonroad-drivability-checker/
Project-URL: Source, https://gitlab.lrz.de/tum-cps/commonroad-drivability-checker
Classifier: Programming Language :: C++
Classifier: Programming Language :: Python :: 3.6
Classifier: Programming Language :: Python :: 3.7
Classifier: Programming Language :: Python :: 3.8
Classifier: License :: OSI Approved :: BSD License
Classifier: Operating System :: POSIX :: Linux
Classifier: Operating System :: MacOS
Requires-Python: >=3.6
License-File: LICENSE
